matpowercaseframes/__init__.py
matpowercaseframes/constants.py
matpowercaseframes/core.py
matpowercaseframes/reader.py
matpowercaseframes/utils.py
matpowercaseframes/version.py
matpowercaseframes-2.0.1.dist-info/licenses/LICENSE.rst
matpowercaseframes-2.0.1.dist-info/METADATA
matpowercaseframes-2.0.1.dist-info/WHEEL
matpowercaseframes-2.0.1.dist-info/top_level.txt
matpowercaseframes-2.0.1.dist-info/RECORD
