Metadata-Version: 2.4
Name: matpowercaseframes
Version: 2.0.1
Summary: Parse MATPOWER case into pandas DataFrame.
Author-email: Muhammad Yasirroni <muhammadyasirroni@gmail.com>
Maintainer-email: Muhammad Yasirroni <muhammadyasirroni@gmail.com>
License: MIT License
Project-URL: Documentation, https://github.com/UGM-EPSLab/matpowercaseframes#readme
Project-URL: Issues, https://github.com/UGM-EPSLab/matpowercaseframes/issues
Project-URL: Source, https://github.com/UGM-EPSLab/matpowercaseframes
Keywords: matpower,parser
Classifier: Programming Language :: Python
Classifier: Programming Language :: Python :: 3.7
Classifier: Programming Language :: Python :: 3.8
Classifier: Programming Language :: Python :: 3.9
Classifier: Programming Language :: Python :: 3.10
Classifier: Programming Language :: Python :: 3.11
Classifier: Programming Language :: Python :: 3.12
Classifier: Programming Language :: Python :: 3.13
Classifier: Programming Language :: Python :: 3.14
Classifier: Topic :: Scientific/Engineering
Classifier: Topic :: Scientific/Engineering :: Mathematics
Classifier: License :: OSI Approved :: MIT License
Classifier: Natural Language :: English
Requires-Python: >=3.7.1
License-File: LICENSE.rst
Requires-Dist: numpy>=1.19.0
Requires-Dist: pandas>=1.2
Provides-Extra: matpower
Requires-Dist: matpower>=7.1.0.2.1.4; extra == "matpower"
Provides-Extra: dev
Requires-Dist: matpower>=7.1.0.2.1.4; extra == "dev"
Requires-Dist: numpy>=1.21.5; extra == "dev"
Requires-Dist: oct2py>=5.5.1; extra == "dev"
Requires-Dist: openpyxl>=3.1.2; extra == "dev"
Requires-Dist: pandas>=1.2.0; extra == "dev"
Requires-Dist: pre-commit>=2.21.0; extra == "dev"
Requires-Dist: pytest>=7.2.0; extra == "dev"
Requires-Dist: pytest-cov>=4.0.0; extra == "dev"
Requires-Dist: pytest-xdist>=3.1.0; extra == "dev"
Requires-Dist: ruff>=0.6.4; extra == "dev"
Dynamic: license-file
